zerofs/__init__.py
zerofs/cache.py
zerofs/file.py
zerofs/fs.py
zerofs/task_queue.py
zerofs-0.2.0.data/scripts/zerofs
zerofs-0.2.0.dist-info/LICENSE
zerofs-0.2.0.dist-info/METADATA
zerofs-0.2.0.dist-info/WHEEL
zerofs-0.2.0.dist-info/top_level.txt
zerofs-0.2.0.dist-info/RECORD
